DoSser/DoSser.py
DoSser/__init__.py
DoSser/teardropAttack.py
DoSser/utils.py
DoSser-1.0.1.dist-info/LICENSE
DoSser-1.0.1.dist-info/METADATA
DoSser-1.0.1.dist-info/WHEEL
DoSser-1.0.1.dist-info/top_level.txt
DoSser-1.0.1.dist-info/RECORD
