Metadata-Version: 2.1
Name: DoSser
Version: 1.0.1
Summary: A layer 4 python Denial of Service tool.
Home-page: https://github.com/BigSlugger/DoSser
Author: Joe Whalley
Author-email: 19095271@stu.mmu.ac.uk
Keywords: python,denial of service,DoS,DDoS
Classifier: Development Status :: 5 - Production/Stable
Classifier: Intended Audience :: Education
Classifier: Programming Language :: Python :: 3
Classifier: License :: OSI Approved :: MIT License
Classifier: Natural Language :: English
Classifier: Operating System :: OS Independent
License-File: LICENSE
Requires-Dist: scapy
Requires-Dist: colorama
